PyEmailerAJM/__init__.py
PyEmailerAJM/_version.py
PyEmailerAJM/py_emailer_ajm.py
PyEmailerAJM/backend/__init__.py
PyEmailerAJM/backend/enums.py
PyEmailerAJM/backend/errs.py
PyEmailerAJM/backend/logger.py
PyEmailerAJM/backend/the_sandman.py
PyEmailerAJM/continuous_monitor/__init__.py
PyEmailerAJM/continuous_monitor/continuous_monitor.py
PyEmailerAJM/continuous_monitor/continuous_monitor_alert_send.py
PyEmailerAJM/continuous_monitor/backend/__init__.py
PyEmailerAJM/continuous_monitor/backend/continuous_colorizer.py
PyEmailerAJM/continuous_monitor/backend/continuous_monitor_base.py
PyEmailerAJM/continuous_monitor/backend/email_state.py
PyEmailerAJM/continuous_monitor/backend/snooze_tracking.py
PyEmailerAJM/msg/__init__.py
PyEmailerAJM/msg/alert_messages.py
PyEmailerAJM/msg/factory.py
PyEmailerAJM/msg/msg.py
PyEmailerAJM/searchers/__init__.py
PyEmailerAJM/searchers/factory.py
PyEmailerAJM/searchers/searchers.py
pyemailerajm-1.9.2.dist-info/licenses/LICENSE.txt
pyemailerajm-1.9.2.dist-info/METADATA
pyemailerajm-1.9.2.dist-info/WHEEL
pyemailerajm-1.9.2.dist-info/top_level.txt
pyemailerajm-1.9.2.dist-info/RECORD
