Metadata-Version: 2.4
Name: PyEmailerAJM
Version: 1.9.2
Summary: Allows for automating sending Email with the Outlook Desktop client. Future releases will add more client support
Home-page: https://github.com/amcsparron2793-Water/PyEmailer
Download-URL: https://github.com/amcsparron2793-Water/PyEmailer/archive/refs/tags/1.9.2.tar.gz
Author: Amcsparron
Author-email: amcsparron@albanyny.gov
License: MIT License
Keywords: Outlook,Email,Automation
License-File: LICENSE.txt
Requires-Dist: pywin32
Requires-Dist: extract_msg
Requires-Dist: email_validator
Requires-Dist: questionary
Requires-Dist: EasyLoggerAJM
Requires-Dist: ColorizerAJM
Dynamic: author
Dynamic: author-email
Dynamic: download-url
Dynamic: home-page
Dynamic: keywords
Dynamic: license
Dynamic: license-file
Dynamic: requires-dist
Dynamic: summary
